xml2ajson/__init__.py
xml2ajson/xml2ajson.py
xml2ajson-0.0.2.dist-info/LICENSE
xml2ajson-0.0.2.dist-info/METADATA
xml2ajson-0.0.2.dist-info/WHEEL
xml2ajson-0.0.2.dist-info/top_level.txt
xml2ajson-0.0.2.dist-info/RECORD
